{
    "menu": [{
            "uri": "pfp",
            "name": "PFP",
            "children": [{
                    "uri": "pfp/rankings",
                    "name": "PFP 랭킹"
                },
                {
                    "uri": "pfp/add",
                    "name": "PFP 등록"
                }
            ]
        },
        {
            "uri": "arts",
            "name": "Arts"
        },
        {
            "uri": "item",
            "name": "Items"
        },
        {
            "uri": "meme",
            "name": "Meme"
        }
    ]
}
